oddoreven/__init__.py
oddoreven/checker.py
oddoreven_afwana-0.0.1.dist-info/METADATA
oddoreven_afwana-0.0.1.dist-info/WHEEL
oddoreven_afwana-0.0.1.dist-info/top_level.txt
oddoreven_afwana-0.0.1.dist-info/RECORD
