Metadata-Version: 2.4
Name: oddoreven_afwana
Version: 0.0.1
Summary: A simple library to check odd or even numbers
Author-email: Afwana Nasar <your_email@example.com>
Project-URL: Homepage, https://github.com/afwana/oddoreven_afwana
Requires-Python: >=3.8
